README.txt
setup.cfg
setup.py
yaco/__init__.py
yaco.applyfun.egg-info/PKG-INFO
yaco.applyfun.egg-info/SOURCES.txt
yaco.applyfun.egg-info/dependency_links.txt
yaco.applyfun.egg-info/entry_points.txt
yaco.applyfun.egg-info/namespace_packages.txt
yaco.applyfun.egg-info/not-zip-safe
yaco.applyfun.egg-info/paster_plugins.txt
yaco.applyfun.egg-info/requires.txt
yaco.applyfun.egg-info/top_level.txt
yaco/applyfun/__init__.py
yaco/applyfun/browser.py
yaco/applyfun/config.py
yaco/applyfun/httplogger.py
yaco/applyfun/tests.py
yaco/applyfun/walker.py
yaco/applyfun/walker_funcs.py
