Metadata-Version: 1.0
Name: yaco.applyfun
Version: 1.0dev
Summary: Apply functions to objects in the ZODB
Home-page: http://www.yaco.es
Author: Yaco S.L.
Author-email: eperez@yaco.es
License: GPL
Platform: UNKNOWN
Classifier: Framework :: Plone
Classifier: Programming Language :: Python
Classifier: Topic :: Software Development :: Libraries :: Python Modules
